crossplane/__init__.py
crossplane/__main__.py
crossplane/analyzer.py
crossplane/builder.py
crossplane/compat.py
crossplane/errors.py
crossplane/ext/__init__.py
crossplane/ext/abstract.py
crossplane/ext/lua.py
crossplane/formatter.py
crossplane/lexer.py
crossplane/parser.py
crossplane_ng-0.5.10.dist-info/AUTHORS.rst
crossplane_ng-0.5.10.dist-info/LICENSE
crossplane_ng-0.5.10.dist-info/METADATA
crossplane_ng-0.5.10.dist-info/NOTICE
crossplane_ng-0.5.10.dist-info/WHEEL
crossplane_ng-0.5.10.dist-info/entry_points.txt
crossplane_ng-0.5.10.dist-info/RECORD
